pyramid_switchboard/__init__.py
pyramid_switchboard/views.py
pyramid_switchboard-0.5.dist-info/DESCRIPTION.rst
pyramid_switchboard-0.5.dist-info/METADATA
pyramid_switchboard-0.5.dist-info/metadata.json
pyramid_switchboard-0.5.dist-info/RECORD
pyramid_switchboard-0.5.dist-info/top_level.txt
pyramid_switchboard-0.5.dist-info/WHEEL
