Metadata-Version: 2.0
Name: pyramid-switchboard
Version: 0.5
Summary: A package which wraps the switchboard feature flipper for Pyramid application development
Home-page: https://github.com/switchboardpy/pyramid_switchboard
Author: Kyle Adams
Author-email: kadams54@gmail.com
License: Apache License
Keywords: wsgi pylons pyramid featureflipper
Platform: UNKNOWN
Classifier: Intended Audience :: Developers
Classifier: Programming Language :: Python
Classifier: Programming Language :: Python :: 2.6
Classifier: Programming Language :: Python :: 2.7
Classifier: Framework :: Pyramid
Classifier: Topic :: Internet :: WWW/HTTP :: WSGI
Classifier: License :: OSI Approved :: Apache Software License
Requires-Dist: pyramid
Requires-Dist: pyramid-mako
Requires-Dist: switchboard (>=1.3.3)
